{
  "metadata": {
    "race": "Tour de France 2026",
    "edition": 113,
    "last_updated": "2026-07-19T20:17:00",
    "source": "procyclingstats.com",
    "version": "2.1"
  },
  "stage": {
    "number": 15,
    "date": "2026-07-19",
    "start": "Champagnole",
    "end": "Plateau de Solaison",
    "distance_km": 183.9,
    "type": "mountain",
    "status": "completed",
    "weather": "مشمس، 23°C",
    "elevation_m": 3200,
    "average_speed_kmh": 41.93,
    "start_time": "13:20",
    "won_how": "Solo attack on final climb",
    "time_limit": "5:13:09 (+0:50:00)",
    "profile_score": 158,
    "gradient_final_km": 7.2,
    "climbs": [
      {"name": "Côte de Champagnole", "category": 3, "km": 35},
      {"name": "Col de la Joux", "category": 2, "km": 85},
      {"name": "Plateau de Solaison", "category": "HC", "km": 183.9}
    ]
  },
  "results": [
    {"rank": 1, "rider": "Remco Evenepoel", "team": "Red Bull - BORA - hansgrohe", "country": "BEL", "time": "4:23:09", "gap": "0:00", "age": 26, "points": 50, "bonus": "10\"", "gc_rank": 2},
    {"rank": 2, "rider": "Tadej Pogačar", "team": "UAE Team Emirates - XRG", "country": "SLO", "time": "4:23:09", "gap": "0:00", "age": 27, "points": 30, "bonus": "6\"", "gc_rank": 1, "jersey": "yellow"},
    {"rank": 3, "rider": "Isaac Del Toro", "team": "UAE Team Emirates - XRG", "country": "MEX", "time": "4:23:15", "gap": "+0:06", "age": 22, "points": 20, "bonus": "4\"", "gc_rank": 3},
    {"rank": 4, "rider": "Paul Seixas", "team": "Decathlon CMA CGM Team", "country": "FRA", "time": "4:24:07", "gap": "+0:58", "age": 19, "points": 18, "gc_rank": 4},
    {"rank": 5, "rider": "Florian Lipowitz", "team": "Red Bull - BORA - hansgrohe", "country": "GER", "time": "4:24:07", "gap": "+0:58", "age": 25, "points": 16, "gc_rank": 5},
    {"rank": 6, "rider": "Lenny Martinez", "team": "Bahrain - Victorious", "country": "FRA", "time": "4:25:06", "gap": "+1:57", "age": 22, "points": 14, "gc_rank": 8},
    {"rank": 7, "rider": "Mattias Skjelmose", "team": "Lidl - Trek", "country": "DEN", "time": "4:25:06", "gap": "+1:57", "age": 25, "points": 12, "gc_rank": 7},
    {"rank": 8, "rider": "Juan Ayuso", "team": "Lidl - Trek", "country": "ESP", "time": "4:25:09", "gap": "+2:00", "age": 23, "points": 10, "gc_rank": 6},
    {"rank": 9, "rider": "Adam Yates", "team": "UAE Team Emirates - XRG", "country": "GBR", "time": "4:25:09", "gap": "+2:00", "age": 33, "points": 8, "gc_rank": 15},
    {"rank": 10, "rider": "Quinn Simmons", "team": "Lidl - Trek", "country": "USA", "time": "4:25:25", "gap": "+2:16", "age": 25, "points": 7, "gc_rank": 18},
    {"rank": 11, "rider": "Jonas Vingegaard", "team": "Team Visma | Lease a Bike", "country": "DEN", "time": "4:26:15", "gap": "+3:06", "age": 29, "points": 6, "gc_rank": 11},
    {"rank": 12, "rider": "Tom Pidcock", "team": "Pinarello Q36.5 Pro Cycling Team", "country": "GBR", "time": "4:26:45", "gap": "+3:36", "age": 26, "points": 5, "gc_rank": 9},
    {"rank": 13, "rider": "Valentin Paret-Peintre", "team": "Soudal Quick-Step", "country": "FRA", "time": "4:27:15", "gap": "+4:06", "age": 25, "points": 5, "gc_rank": 14},
    {"rank": 14, "rider": "Richard Carapaz", "team": "EF Education - EasyPost", "country": "ECU", "time": "4:27:45", "gap": "+4:36", "age": 33, "points": 5, "gc_rank": 16},
    {"rank": 15, "rider": "Davide Piganzoli", "team": "Team Visma | Lease a Bike", "country": "ITA", "time": "4:28:15", "gap": "+5:06", "age": 23, "points": 5, "gc_rank": 17},
    {"rank": 16, "rider": "Kévin Vauquelin", "team": "Netcompany INEOS", "country": "FRA", "time": "4:28:45", "gap": "+5:36", "age": 24, "points": 0, "gc_rank": 19},
    {"rank": 17, "rider": "Brandon McNulty", "team": "UAE Team Emirates - XRG", "country": "USA", "time": "4:29:15", "gap": "+6:06", "age": 27, "points": 0, "gc_rank": 20},
    {"rank": 18, "rider": "Mads Pedersen", "team": "Lidl - Trek", "country": "DEN", "time": "4:35:20", "gap": "+12:11", "age": 30, "points": 0, "gc_rank": 22, "jersey": "green"},
    {"rank": 19, "rider": "Jasper Philipsen", "team": "Alpecin - Premier Tech", "country": "BEL", "time": "4:35:20", "gap": "+12:11", "age": 28, "points": 0, "gc_rank": 24},
    {"rank": 20, "rider": "Biniam Girmay", "team": "NSN Cycling Team", "country": "ERI", "time": "4:35:20", "gap": "+12:11", "age": 26, "points": 0, "gc_rank": 26}
  ],
  "points_classification": [
    {"rank": 1, "rider": "Mads Pedersen", "team": "Lidl - Trek", "country": "DEN", "points": 417, "jersey": "green"},
    {"rank": 2, "rider": "Jasper Philipsen", "team": "Alpecin - Premier Tech", "country": "BEL", "points": 386},
    {"rank": 3, "rider": "Biniam Girmay", "team": "NSN Cycling Team", "country": "ERI", "points": 361},
    {"rank": 4, "rider": "Max Kanter", "team": "XDS Astana Team", "country": "GER", "points": 271},
    {"rank": 5, "rider": "Olav Kooij", "team": "Decathlon CMA CGM Team", "country": "NED", "points": 210},
    {"rank": 6, "rider": "Søren Wærenskjold", "team": "Uno-X Mobility", "country": "NOR", "points": 159},
    {"rank": 7, "rider": "Tadej Pogačar", "team": "UAE Team Emirates - XRG", "country": "SLO", "points": 144},
    {"rank": 8, "rider": "Anthony Turgis", "team": "TotalEnergies", "country": "FRA", "points": 129},
    {"rank": 9, "rider": "Milan Fretin", "team": "Cofidis", "country": "BEL", "points": 117},
    {"rank": 10, "rider": "Isaac Del Toro", "team": "UAE Team Emirates - XRG", "country": "MEX", "points": 112}
  ],
  "kom_classification": [
    {"rank": 1, "rider": "Tadej Pogačar", "team": "UAE Team Emirates - XRG", "country": "SLO", "points": 67, "jersey": "polka_dot"},
    {"rank": 2, "rider": "Valentin Paret-Peintre", "team": "Soudal Quick-Step", "country": "FRA", "points": 45},
    {"rank": 3, "rider": "Richard Carapaz", "team": "EF Education - EasyPost", "country": "ECU", "points": 39},
    {"rank": 4, "rider": "Paul Seixas", "team": "Decathlon CMA CGM Team", "country": "FRA", "points": 34},
    {"rank": 5, "rider": "Remco Evenepoel", "team": "Red Bull - BORA - hansgrohe", "country": "BEL", "points": 31},
    {"rank": 6, "rider": "Isaac Del Toro", "team": "UAE Team Emirates - XRG", "country": "MEX", "points": 30},
    {"rank": 7, "rider": "Tom Pidcock", "team": "Pinarello Q36.5 Pro Cycling Team", "country": "GBR", "points": 28},
    {"rank": 8, "rider": "Lenny Martinez", "team": "Bahrain - Victorious", "country": "FRA", "points": 22},
    {"rank": 9, "rider": "Florian Lipowitz", "team": "Red Bull - BORA - hansgrohe", "country": "GER", "points": 20},
    {"rank": 10, "rider": "Nicolas Prodhomme", "team": "Decathlon CMA CGM Team", "country": "FRA", "points": 17}
  ],
  "youth_classification": [
    {"rank": 1, "rider": "Isaac Del Toro", "team": "UAE Team Emirates - XRG", "country": "MEX", "time": "55:47:29", "gap": "0:00", "age": 22, "jersey": "white"},
    {"rank": 2, "rider": "Paul Seixas", "team": "Decathlon CMA CGM Team", "country": "FRA", "time": "55:47:54", "gap": "+0:25", "age": 19},
    {"rank": 3, "rider": "Juan Ayuso", "team": "Lidl - Trek", "country": "ESP", "time": "55:48:59", "gap": "+1:30", "age": 23},
    {"rank": 4, "rider": "Lenny Martinez", "team": "Bahrain - Victorious", "country": "FRA", "time": "55:51:59", "gap": "+4:30", "age": 22},
    {"rank": 5, "rider": "Davide Piganzoli", "team": "Team Visma | Lease a Bike", "country": "ITA", "time": "56:06:13", "gap": "+18:44", "age": 23},
    {"rank": 6, "rider": "Quinn Simmons", "team": "Lidl - Trek", "country": "USA", "time": "57:05:01", "gap": "+1:17:32", "age": 25},
    {"rank": 7, "rider": "Lennert Van Eetvelt", "team": "Lotto Intermarché", "country": "BEL", "time": "57:15:04", "gap": "+1:27:35", "age": 24},
    {"rank": 8, "rider": "Pablo Castrillo", "team": "Movistar Team", "country": "ESP", "time": "57:15:34", "gap": "+1:28:05", "age": 25},
    {"rank": 9, "rider": "Kévin Vauquelin", "team": "Netcompany INEOS", "country": "FRA", "time": "57:24:48", "gap": "+1:37:19", "age": 24},
    {"rank": 10, "rider": "Antonio Tiberi", "team": "Bahrain - Victorious", "country": "ITA", "time": "57:35:57", "gap": "+1:48:28", "age": 25}
  ],
  "statistics": {
    "total_participants": 184,
    "finished": 182,
    "dnf": 2,
    "average_speed_kmh": 41.93,
    "fastest_avg_kmh": 41.93,
    "youngest_rider": {"name": "Paul Seixas", "age": 19},
    "oldest_rider": {"name": "Adam Yates", "age": 33},
    "temperature_c": 23,
    "top_teams": [
      {"name": "UAE Team Emirates - XRG", "riders": 8},
      {"name": "Lidl - Trek", "riders": 8},
      {"name": "Team Visma | Lease a Bike", "riders": 8},
      {"name": "Red Bull - BORA - hansgrohe", "riders": 8},
      {"name": "Decathlon CMA CGM Team", "riders": 8}
    ]
  },
  "jerseys": {
    "yellow": {"name": "Tadej Pogačar", "team": "UAE Team Emirates - XRG", "reason": "المتصدر العام - 55:41:31"},
    "green": {"name": "Mads Pedersen", "team": "Lidl - Trek", "reason": "متصدر ترتيب النقاط - 417 نقطة"},
    "polka_dot": {"name": "Tadej Pogačar", "team": "UAE Team Emirates - XRG", "reason": "متصدر تسلق الجبال - 67 نقطة"},
    "white": {"name": "Isaac Del Toro", "team": "UAE Team Emirates - XRG", "reason": "أفضل شاب (22 سنة) - انتزع القميص الأبيض"}
  },
  "general_classification_after_stage": {
    "top_10": [
      {"rank": 1, "rider": "Tadej Pogačar", "team": "UAE Team Emirates - XRG", "country": "SLO", "time": "55:41:31", "gap": "0:00"},
      {"rank": 2, "rider": "Remco Evenepoel", "team": "Red Bull - BORA - hansgrohe", "country": "BEL", "time": "55:46:31", "gap": "+5:00"},
      {"rank": 3, "rider": "Isaac Del Toro", "team": "UAE Team Emirates - XRG", "country": "MEX", "time": "55:47:29", "gap": "+5:58"},
      {"rank": 4, "rider": "Paul Seixas", "team": "Decathlon CMA CGM Team", "country": "FRA", "time": "55:47:54", "gap": "+6:23"},
      {"rank": 5, "rider": "Florian Lipowitz", "team": "Red Bull - BORA - hansgrohe", "country": "GER", "time": "55:48:19", "gap": "+6:48"},
      {"rank": 6, "rider": "Juan Ayuso", "team": "Lidl - Trek", "country": "ESP", "time": "55:48:59", "gap": "+7:28"},
      {"rank": 7, "rider": "Mattias Skjelmose", "team": "Lidl - Trek", "country": "DEN", "time": "55:51:09", "gap": "+9:38"},
      {"rank": 8, "rider": "Lenny Martinez", "team": "Bahrain - Victorious", "country": "FRA", "time": "55:51:59", "gap": "+10:28"},
      {"rank": 9, "rider": "Tom Pidcock", "team": "Pinarello Q36.5 Pro Cycling Team", "country": "GBR", "time": "55:52:50", "gap": "+11:19"},
      {"rank": 10, "rider": "Jordan Jegat", "team": "TotalEnergies", "country": "FRA", "time": "56:00:57", "gap": "+19:26"}
    ]
  }
}
